{
    "version": "0.10.0",
    "architecture": {
        "64bit": {
            "url": "https://github.com/KusionStack/kusion/releases/download/v0.10.0/kusion_0.10.0_windows_amd64.zip",
            "bin": [
                "kusion.exe"
            ],
            "hash": "c5af630dc3dbde613ea79974d51da8a5e0da983fb5eaf045d334549a1feb5d00"
        }
    },
    "homepage": "http://github.com/KusionStack/kusion",
    "license": "Apache License 2.0",
    "description": "Codify and deliver intentions to Kubernetes and Clouds."
}